LICENSE.md
README.md
setup.cfg
setup.py
xml2csv.py
GISxml2csv.egg-info/PKG-INFO
GISxml2csv.egg-info/SOURCES.txt
GISxml2csv.egg-info/dependency_links.txt
GISxml2csv.egg-info/entry_points.txt
GISxml2csv.egg-info/top_level.txt